wcmatch/__init__.py
wcmatch/__meta__.py
wcmatch/_wcmatch.py
wcmatch/_wcparse.py
wcmatch/fnmatch.py
wcmatch/glob.py
wcmatch/pathlib.py
wcmatch/posix.py
wcmatch/py.typed
wcmatch/util.py
wcmatch/wcmatch.py
wcmatch-8.3.dist-info/LICENSE.md
wcmatch-8.3.dist-info/METADATA
wcmatch-8.3.dist-info/WHEEL
wcmatch-8.3.dist-info/top_level.txt
wcmatch-8.3.dist-info/RECORD
