Metadata-Version: 2.1
Name: wcmatch
Version: 8.3
Summary: Wildcard/glob file name matcher.
Home-page: https://github.com/facelessuser/wcmatch
Author: Isaac Muse
Author-email: Isaac.Muse@gmail.com
License: MIT License
Keywords: glob fnmatch search wildcard
Platform: UNKNOWN
Classifier: Development Status :: 5 - Production/Stable
Classifier: Intended Audience :: Developers
Classifier: License :: OSI Approved :: MIT License
Classifier: Operating System :: OS Independent
Classifier: Programming Language :: Python :: 3
Classifier: Programming Language :: Python :: 3.6
Classifier: Programming Language :: Python :: 3.7
Classifier: Programming Language :: Python :: 3.8
Classifier: Programming Language :: Python :: 3.9
Classifier: Programming Language :: Python :: 3.10
Classifier: Topic :: Software Development :: Libraries :: Python Modules
Classifier: Typing :: Typed
Requires-Python: >=3.6
License-File: LICENSE.md
